app/__init__.py
app/auth.py
app/main.py
app/user_store.py
offline_mfa-1.0.0.dist-info/licenses/LICENSE
offline_mfa-1.0.0.dist-info/METADATA
offline_mfa-1.0.0.dist-info/WHEEL
offline_mfa-1.0.0.dist-info/entry_points.txt
offline_mfa-1.0.0.dist-info/top_level.txt
offline_mfa-1.0.0.dist-info/RECORD
