Metadata-Version: 2.4
Name: offline_mfa
Version: 1.0.0
Summary: A secure offline MFA system using TOTP
Home-page: https://github.com/yourusername/offline_mfa
Author: Abhishek N Nairy
Author-email: n.abhishek@isteer.com
License: MIT
Classifier: Programming Language :: Python :: 3
Classifier: License :: OSI Approved :: MIT License
Classifier: Operating System :: OS Independent
Requires-Python: >=3.7
License-File: LICENSE
Requires-Dist: pyotp
Requires-Dist: cryptography
Requires-Dist: mysql-connector-python
Requires-Dist: python-dotenv
Dynamic: author
Dynamic: author-email
Dynamic: classifier
Dynamic: description-content-type
Dynamic: home-page
Dynamic: license-file
Dynamic: requires-dist
Dynamic: requires-python
Dynamic: summary
